parse_emails/__init__.py
parse_emails/common.py
parse_emails/constants.py
parse_emails/handle_eml.py
parse_emails/handle_msg.py
parse_emails/parse_emails.py
parse_emails/tests/__init__.py
parse_emails/tests/parse_emails_test.py
parse_emails/tests/test_data/DONT_OPEN-MALICIOUS.eml
parse_emails/tests/test_data/DONT_OPEN-MALICIOUS_base64_headers.eml
parse_emails/tests/test_data/Fwd_test-inner_attachment_eml.eml
parse_emails/tests/test_data/ParseEmailFiles-test-emls.eml
parse_emails/tests/test_data/Phishing_TEST.msg
parse_emails/tests/test_data/chinese_big5_encoding.eml
parse_emails/tests/test_data/chinese_email_test.eml
parse_emails/tests/test_data/chinese_gb2312_encoding.eml
parse_emails/tests/test_data/chinese_gbk_encoding.eml
parse_emails/tests/test_data/chinese_iso_2022_jp_encoding.eml
parse_emails/tests/test_data/containing_corrupted_eml.eml
parse_emails/tests/test_data/email_with_signed_attachment.eml
parse_emails/tests/test_data/email_with_special_char_bytes.eml
parse_emails/tests/test_data/embedded_base64_eml.eml
parse_emails/tests/test_data/eml_contains_base64_eml.eml
parse_emails/tests/test_data/eml_contains_base64_eml2.eml
parse_emails/tests/test_data/eml_contains_emptytxt_htm_file.eml
parse_emails/tests/test_data/eml_contains_htm_attachment.eml
parse_emails/tests/test_data/eml_contains_htm_content_type.eml
parse_emails/tests/test_data/eml_contains_image_as_cid.eml
parse_emails/tests/test_data/eml_contains_image_name_with_Thai_characters.eml
parse_emails/tests/test_data/eml_non_ascii.eml
parse_emails/tests/test_data/eml_with_special_utf_8_chars.eml
parse_emails/tests/test_data/file_with_a_long_subject_and_special_characters.eml
parse_emails/tests/test_data/html_attachment.msg
parse_emails/tests/test_data/image.jpg
parse_emails/tests/test_data/invalid_message_id.eml
parse_emails/tests/test_data/msg_contains_eml.msg
parse_emails/tests/test_data/msg_with_null_characters_in_ascii_decode.msg
parse_emails/tests/test_data/msg_with_rtf_compressed.msg
parse_emails-0.1.48.dist-info/LICENSE
parse_emails-0.1.48.dist-info/METADATA
parse_emails-0.1.48.dist-info/WHEEL
parse_emails-0.1.48.dist-info/RECORD
