Metadata-Version: 2.1
Name: parse-emails
Version: 0.1.48
Summary: Parses an email message file and extracts the data from it.
License: MIT
Author: Demisto
Requires-Python: >=3.9,<3.13
Classifier: Intended Audience :: Developers
Classifier: License :: OSI Approved :: MIT License
Classifier: Natural Language :: English
Classifier: Programming Language :: Python :: 3
Classifier: Programming Language :: Python :: 3.9
Classifier: Programming Language :: Python :: 3.10
Classifier: Programming Language :: Python :: 3.11
Classifier: Programming Language :: Python :: 3.12
Classifier: Programming Language :: Python :: 3.7
Classifier: Programming Language :: Python :: 3.8
Classifier: Programming Language :: Python :: Implementation :: CPython
Requires-Dist: RTFDE
Requires-Dist: chardet
Requires-Dist: compressed_rtf
Requires-Dist: datetime
Requires-Dist: jira (>=3.8.0,<4.0.0)
Requires-Dist: junitparser (>=3.1.2,<4.0.0)
Requires-Dist: olefile
Requires-Dist: pip
Requires-Dist: pyopenssl
Requires-Dist: pypandoc
Requires-Dist: pytest
Requires-Dist: python-gitlab (>=3.0.0,<4.0.0)
Requires-Dist: python-magic
Requires-Dist: slack-sdk
